humerly_mcp_demo/__init__.py
humerly_mcp_demo-0.1.0.dist-info/METADATA
humerly_mcp_demo-0.1.0.dist-info/WHEEL
humerly_mcp_demo-0.1.0.dist-info/entry_points.txt
humerly_mcp_demo-0.1.0.dist-info/RECORD
