Metadata-Version: 2.4
Name: humerly-mcp-demo
Version: 0.1.0
Summary: Add your description here
Author-email: "157982867+Humerly@users.noreply.github.com" <157982867+Humerly@users.noreply.github.com>
Requires-Python: >=3.11
Requires-Dist: mcp[cli]>=1.11.0
